leno/__init__.py
leno/__main__.py
leno/cli.py
leno/lib.py
leno/source.py
leno-0.1.0.dist-info/LICENSE
leno-0.1.0.dist-info/METADATA
leno-0.1.0.dist-info/WHEEL
leno-0.1.0.dist-info/entry_points.txt
leno-0.1.0.dist-info/RECORD
